{
  "type": "pfm:furniture",
  "group": "kitchen",
  "ingredients": [
    {
      "item": "modernlife:diorite_barrier"
    },
    {
      "item": "modernlife:diorite_barrier"
    },
    {
      "item": "modernlife:diorite_barrier"
    },
    {
      "item": "modernlife:diorite_barrier"
    },
    {
      "item": "modernlife:diorite_barrier"
    },
    {
      "item": "modernlife:polished_diorite_barrier"
    },
    {
      "item": "modernlife:polished_diorite_barrier"
    },
    {
      "item": "modernlife:polished_diorite_barrier"
    },
    {
      "item": "minecraft:furnace"
    }
  ],
  "result": {
    "item": "pfm:diorite_barrier_modernlife_kitchen_counter_oven"
  }
}